nfc/__init__.py
nfc/__main__.py
nfc/dep.py
nfc/clf/__init__.py
nfc/clf/acr122.py
nfc/clf/arygon.py
nfc/clf/device.py
nfc/clf/pn531.py
nfc/clf/pn532.py
nfc/clf/pn533.py
nfc/clf/pn53x.py
nfc/clf/rcs380.py
nfc/clf/rcs956.py
nfc/clf/transport.py
nfc/clf/udp.py
nfc/handover/__init__.py
nfc/handover/client.py
nfc/handover/server.py
nfc/llcp/__init__.py
nfc/llcp/err.py
nfc/llcp/llc.py
nfc/llcp/pdu.py
nfc/llcp/sec.py
nfc/llcp/socket.py
nfc/llcp/tco.py
nfc/snep/__init__.py
nfc/snep/client.py
nfc/snep/server.py
nfc/tag/__init__.py
nfc/tag/tt1.py
nfc/tag/tt1_broadcom.py
nfc/tag/tt2.py
nfc/tag/tt2_nxp.py
nfc/tag/tt3.py
nfc/tag/tt3_sony.py
nfc/tag/tt4.py
nfcpy-1.0.4.dist-info/LICENSE
nfcpy-1.0.4.dist-info/METADATA
nfcpy-1.0.4.dist-info/WHEEL
nfcpy-1.0.4.dist-info/top_level.txt
nfcpy-1.0.4.dist-info/RECORD
