Metadata-Version: 2.1
Name: nfcpy
Version: 1.0.4
Summary: Python module for Near Field Communication.
Home-page: https://github.com/nfcpy/nfcpy
Author: Stephen Tiedemann
Author-email: stephen.tiedemann@gmail.com
Maintainer: Stephen Tiedemann
Maintainer-email: stephen.tiedemann@gmail.com
License: EUPL
Keywords: contactless,nfc,llcp,p2p,snep
Platform: UNKNOWN
Classifier: Development Status :: 5 - Production/Stable
Classifier: Intended Audience :: Developers
Classifier: Natural Language :: English
Classifier: Programming Language :: Python :: 2
Classifier: Programming Language :: Python :: 2.6
Classifier: Programming Language :: Python :: 2.7
Classifier: Programming Language :: Python :: 3.6
Classifier: Programming Language :: Python :: 3.7
Classifier: Programming Language :: Python :: 3.8
Classifier: Programming Language :: Python :: 3.9
Classifier: Operating System :: POSIX :: Linux
Classifier: Operating System :: MacOS :: MacOS X
Classifier: Operating System :: Microsoft :: Windows
Classifier: Topic :: Software Development :: Libraries :: Python Modules
Classifier: License :: OSI Approved :: European Union Public Licence 1.1 (EUPL 1.1)
Requires-Python: >=2.6
License-File: LICENSE
